{"name": "JuL", "image_url": "https://images.genius.com/1649cadae9409b0287e4abac7b713058.1000x525x11.gif", "sexe": "Men", "type": "Individual","vocab_length": 2310, "vocab": {"je": 311, "fume": 35, "des": 187, "grosses": 2, "barres": 1, "m": 235, "etouffe": 1, "il": 66, "me": 117, "reste": 16, "2": 1, "sticks": 2, "mets": 29, "tout": 98, "j": 898, "ai": 158, "fait": 82, "un": 106, "reve": 13, "38": 1, "ans": 6, "disais": 1, "au": 66, "patron": 1, "guette": 1, "ou": 52, "sors": 28, "de": 250, "chez": 12, "moi": 145, "cale": 3, "entends": 6, "akha": 1, "descente": 1, "ca": 111, "finit": 2, "palais": 3, "famille": 8, "en": 277, "pleurs": 1, "stressante": 1, "trop": 88, "miss": 10, "qui": 121, "pistent": 1, "autour": 4, "la": 447, "piste": 7, "filles": 7, "bien": 18, "bitchs": 1, "vite": 6, "y": 198, "a": 475, "embrouille": 8, "nique": 12, "les": 248, "videurs": 1, "meme": 63, "eux": 10, "c": 288, "est": 349, "fils": 9, "p": 17, "grosse": 2, "droite": 1, "faut": 51, "leur": 6, "faire": 49, "tomber": 2, "le": 398, "taser": 2, "poto": 23, "s": 146, "niquer": 4, "veut": 18, "revenir": 1, "avec": 34, "fazer": 2, "suis": 209, "chien": 2, "malade": 22, "pas": 465, "pour": 113, "5": 6, "t": 371, "as": 78, "assume": 1, "braquage": 2, "ils": 84, "ont": 16, "rajoute": 1, "25": 1, "si": 85, "sais": 61, "pourquoi": 28, "maintenant": 6, "tu": 398, "veux": 64, "nous": 43, "mais": 138, "inquietes": 1, "fais": 173, "ce": 56, "soir": 19, "oublie": 27, "cherche": 7, "mon": 138, "chemin": 4, "detours": 4, "et": 170, "quand": 104, "repense": 5, "jour": 15, "dis": 57, "qu": 215, "vie": 57, "courte": 4, "on": 212, "partira": 4, "tous": 33, "alors": 57, "tape": 10, "vos": 7, "discours": 4, "derriere": 7, "bonheur": 8, "cours": 9, "jul": 27, "arrive": 20, "dans": 213, "l": 289, "game": 11, "venu": 2, "trainais": 1, "gens": 12, "jamais": 17, "profite": 2, "evite": 2, "coups": 9, "d": 194, "putes": 6, "salopes": 1, "aiment": 3, "friques": 1, "sache": 2, "avant": 6, "pauvre": 1, "coeur": 26, "piquer": 1, "shakira": 1, "comme": 77, "pique": 1, "vas": 45, "rends": 2, "briquet": 1, "roule": 7, "buvette": 5, "prends": 12, "virages": 1, "ci": 2, "frerot": 3, "rappe": 5, "degun": 6, "fini": 16, "embrouilles": 4, "histoire": 30, "fou": 23, "frappait": 2, "tekken": 1, "youv": 1, "es": 168, "mis": 15, "tes": 35, "mains": 2, "merde": 19, "t1": 1, "potos": 15, "perdent": 1, "face": 2, "branchent": 2, "ta": 53, "femme": 4, "casse": 9, "une": 40, "nuit": 13, "blanche": 1, "couilles": 5, "suffit": 6, "verre": 1, "bois": 2, "tasse": 5, "eu": 1, "etait": 5, "sur": 60, "ma": 210, "mere": 23, "oeil": 3, "mal": 22, "lune": 6, "fumer": 1, "vient": 7, "sortir": 6, "continue": 1, "assumer": 3, "garde": 3, "tete": 45, "epaules": 1, "folles": 4, "maudissent": 1, "esquive": 12, "taule": 3, "lol": 2, "gros": 41, "diss": 1, "quoi": 25, "dise": 3, "dit": 26, "rien": 105, "prouver": 3, "donne": 10, "ton": 59, "amour": 9, "tchiki": 21, "tchikita": 30, "x2": 2, "elle": 236, "regard": 6, "tue": 4, "cheveux": 7, "longs": 4, "nikita": 3, "quitte": 9, "passe": 38, "toute": 25, "peloter": 1, "del": 3, "que": 202, "cote": 2, "regarde": 14, "yeux": 20, "sirotant": 1, "cocktai": 1, "vu": 24, "vip": 5, "prend": 3, "mec": 8, "mortel": 1, "sait": 20, "manque": 5, "lui": 10, "sa": 14, "gram": 1, "snap": 1, "facebook": 1, "instagram": 1, "parler": 13, "grande": 1, "madame": 6, "toi": 170, "vis": 17, "toujours": 8, "bas": 7, "gamme": 1, "plonge": 2, "ses": 11, "noie": 3, "vois": 82, "etais": 12, "girl": 2, "imaginais": 1, "seul": 81, "fois": 14, "gueule": 4, "fiers": 1, "engueule": 1, "plus": 93, "devant": 13, "son": 33, "boule": 12, "magique": 3, "evade": 2, "deviens": 2, "tres": 4, "nostalgique": 1, "belle": 21, "ouais": 76, "ongles": 1, "plaques": 1, "longo": 1, "aime": 40, "gentille": 1, "simple": 1, "besoin": 2, "aller": 7, "chercher": 1, "lambo": 2, "trouve": 10, "beau": 5, "fuis": 1, "te": 157, "fuit": 1, "x8": 1, "ju": 6, "big": 3, "up": 1, "dj": 1, "babs": 1, "amoureux": 2, "repond": 1, "tel": 1, "petes": 1, "plombs": 1, "bordel": 3, "talons": 2, "rimmel": 1, "potes": 14, "meurs": 2, "oui": 18, "va": 33, "croire": 3, "cousine": 1, "champagne": 1, "monde": 20, "joue": 15, "kiss": 1, "fort": 9, "peut": 9, "finir": 7, "hotel": 2, "ibis": 1, "n": 37, "ecoute": 8, "honte": 2, "crois": 25, "gentil": 3, "prise": 1, "photo": 4, "fin": 1, "soiree": 2, "charger": 4, "moto": 7, "regardes": 3, "se": 26, "dos": 9, "400": 4, "fasse": 8, "accro": 3, "car": 9, "love": 15, "drogue": 8, "vraiment": 10, "tourner": 3, "rebelle": 1, "baisses": 1, "peux": 17, "choisir": 1, "autre": 26, "bonne": 4, "problemes": 5, "avoir": 8, "tonnes": 2, "encore": 6, "restes": 2, "faudra": 2, "etonnes": 1, "juste": 2, "conseil": 1, "sens": 17, "ici": 14, "beaucoup": 15, "touche": 6, "fond": 2, "100": 3, "cette": 5, "heure": 10, "pris": 6, "con": 6, "non": 18, "deconner": 1, "elles": 5, "veulent": 9, "toutes": 5, "monnaie": 2, "petit": 13, "bourge": 1, "pigeonner": 1, "par": 13, "chomer": 1, "connais": 10, "trimbaler": 1, "journee": 2, "payes": 1, "400EUR": 1, "fourrer": 2, "paranoia": 14, "paranoiaque": 10, "laissez": 12, "route": 6, "foutre": 16, "amis": 5, "ennemis": 6, "calomnie": 1, "hey": 1, "vier": 1, "colombie": 3, "snoop": 1, "dogg": 1, "tieq": 1, "vend": 3, "douce": 2, "who": 1, "smoke": 1, "couz": 4, "fuck": 1, "troque": 1, "dites": 9, "change": 7, "test": 6, "attends": 4, "what": 1, "your": 4, "name": 1, "femmes": 4, "valent": 1, "gamberges": 1, "finis": 2, "repars": 1, "balles": 1, "zingueur": 1, "coupes": 2, "kil": 1, "voleur": 1, "coinceur": 1, "sont": 29, "traitres": 5, "malefiques": 1, "quittes": 1, "cite": 2, "simplement": 1, "piquet": 1, "vide": 1, "prada": 2, "videur": 5, "pointues": 1, "pointures": 1, "parking": 1, "ceinture": 1, "dur": 12, "voir": 22, "glisser": 1, "sol": 3, "tarpin": 2, "fautes": 1, "suivre": 1, "tente": 3, "chance": 3, "rentrer": 8, "legende": 2, "apres": 10, "disent": 3, "calcule": 4, "acquis": 2, "ville": 4, "armes": 8, "jusqu": 4, "aux": 12, "dents": 3, "amazonie": 2, "ne": 48, "mia": 2, "facon": 2, "nos": 2, "jours": 8, "peu": 14, "fiables": 1, "grille": 3, "changer": 1, "faudrait": 2, "miracle": 1, "joues": 1, "pote": 2, "ouvert": 1, "ouh": 3, "mamma": 1, "vous": 17, "faites": 2, "chier": 1, "jugerai": 1, "sans": 20, "savoir": 4, "faible": 1, "demande": 15, "dieu": 8, "guider": 3, "vider": 2, "killer": 5, "fantastique": 5, "rentre": 10, "asics": 7, "viens": 27, "donc": 13, "my": 9, "world": 6, "deuh": 5, "fatigues": 5, "fumes": 5, "du": 52, "plastique": 5, "bouge": 15, "body": 15, "ah": 17, "yeah": 3, "oh": 51, "ooo": 6, "tirer": 4, "loin": 13, "iras": 4, "marcheras": 1, "monteras": 1, "tard": 4, "tuera": 1, "loi": 2, "milieu": 1, "go": 11, "charge": 6, "corrida": 1, "sert": 5, "gorilla": 1, "rappelles": 1, "riiez": 1, "etes": 2, "heureusement": 1, "trie": 1, "regrette": 2, "ces": 5, "biatchs": 1, "pepe": 1, "font": 6, "grillade": 1, "mordent": 1, "crier": 2, "cherchent": 1, "suite": 1, "kyriad": 1, "puis": 3, "gamberge": 2, "choses": 7, "maniere": 1, "tant": 11, "mieux": 5, "marche": 2, "miel": 5, "monte": 3, "air": 9, "coup": 15, "reins": 1, "crie": 3, "nom": 3, "deux": 11, "trois": 2, "belles": 3, "paroles": 3, "homme": 2, "wesh": 35, "allez": 11, "let": 2, "parlent": 10, "laisse": 17, "tiens": 2, "gadji": 1, "voit": 5, "fesses": 4, "baise": 9, "dirai": 2, "baffes": 3, "tours": 2, "quartier": 7, "mort": 6, "leve": 6, "main": 2, "beuh": 23, "plaquette": 6, "claquettes": 4, "carre": 5, "survet": 8, "prendre": 11, "sang": 12, "honda": 6, "mes": 57, "sons": 6, "tournent": 3, "jonque": 1, "trahi": 10, "bon": 15, "gars": 4, "fumette": 7, "trompe": 1, "oses": 2, "demander": 2, "comment": 7, "appelle": 24, "chose": 5, "laisez": 2, "tranquille": 3, "court": 2, "idees": 2, "sec": 2, "coucher": 2, "cabre": 10, "a7": 2, "jaloux": 17, "ecoutent": 2, "cachette": 2, "bled": 2, "cassette": 2, "coffre": 2, "billets": 10, "sorti": 2, "r1": 2, "tournes": 2, "plaque": 3, "plie": 1, "mathy": 1, "mimie": 1, "team": 8, "imite": 3, "bleu": 3, "vers": 3, "minuit": 1, "blesser": 1, "mimi": 2, "valeurs": 14, "depuis": 5, "dois": 2, "loves": 2, "revoir": 2, "vais": 42, "dire": 16, "cross": 8, "vole": 10, "roue": 8, "voilee": 8, "petard": 9, "violets": 8, "deshabille": 10, "violer": 16, "kalif": 2, "hardcore": 1, "demarre": 1, "quart": 1, "tour": 3, "violent": 1, "quad": 1, "carrefour": 1, "emmene": 10, "ok": 2, "histoires": 2, "mele": 3, "ramene": 2, "mecs": 2, "vrais": 4, "mettent": 3, "levage": 1, "kalash": 3, "auto": 1, "serein": 1, "tieks": 7, "flics": 2, "prennent": 15, "anti": 3, "etat": 2, "locale": 1, "vida": 2, "loca": 5, "scooteur": 1, "local": 1, "honnete": 1, "allure": 1, "comete": 1, "commeres": 1, "doigt": 2, "maire": 1, "aider": 2, "niquez": 1, "meres": 1, "temps": 29, "petits": 17, "volent": 1, "tot": 3, "marseille": 13, "crame": 3, "evasion": 1, "helico": 2, "vito": 1, "honneur": 1, "vital": 2, "calibre": 1, "vuitton": 2, "attentat": 1, "lyrical": 1, "schmits": 4, "arah": 3, "taille": 2, "panique": 1, "celui": 2, "ravitaille": 1, "stud": 4, "sous": 30, "pollen": 1, "mc": 5, "dirais": 1, "demain": 2, "voiture": 3, "rend": 5, "bombe": 2, "embarque": 1, "jogging": 2, "tarc": 1, "degaine": 4, "paul": 1, "shark": 1, "charcler": 1, "frere": 14, "parloir": 1, "matons": 1, "haut": 2, "parleur": 1, "22": 1, "geoles": 1, "juge": 3, "remballe": 1, "recuperer": 1, "para": 1, "balai": 1, "pilotage": 1, "rappeurs": 1, "chaler": 2, "cabrer": 1, "toucher": 1, "bavette": 1, "guerre": 1, "simo": 1, "troue": 2, "corps": 5, "perceuse": 1, "peur": 10, "personne": 13, "parle": 20, "frissonne": 1, "sonne": 3, "volaille": 1, "circule": 1, "pieds": 2, "vendeurs": 1, "treve": 1, "arrete": 3, "source": 1, "traites": 1, "pet": 2, "soufflette": 2, "encodeuse": 1, "cash": 3, "phuket": 1, "gaffe": 5, "guettes": 2, "petent": 1, "gueules": 2, "aimes": 18, "rap": 14, "danse": 10, "single": 1, "1": 3, "3": 3, "zone": 8, "vert": 1, "jungle": 1, "appart": 6, "pousser": 2, "purple": 1, "pare": 2, "balle": 2, "foutent": 1, "ecole": 1, "shit": 11, "cartable": 1, "liga": 12, "one": 13, "base": 2, "cartonne": 1, "piller": 1, "cambu": 2, "carlton": 1, "chaud": 4, "mans": 1, "peter": 2, "naiman": 1, "schema": 1, "blonde": 2, "met": 9, "chameau": 1, "rhamo": 1, "malle": 3, "16": 2, "braque": 2, "secondes": 1, "sacs": 1, "arriere": 1, "rambo": 2, "testo": 1, "espere": 1, "mourir": 3, "cess": 1, "pauvres": 1, "riches": 1, "bouriche": 1, "bourres": 1, "blu": 1, "ray": 1, "gadjis": 3, "jolie": 82, "dame": 2, "flashe": 2, "danser": 2, "tremble": 1, "veille": 1, "tombe": 2, "bouche": 3, "tanke": 1, "detende": 1, "teuplait": 1, "detends": 7, "blues": 1, "perdu": 4, "recoudrai": 1, "balafres": 4, "hola": 2, "senora": 8, "aura": 9, "saches": 2, "gomorra": 2, "jeu": 7, "penses": 7, "choque": 19, "lova": 24, "souffle": 1, "canon": 2, "souffre": 1, "saoule": 4, "plais": 2, "voulais": 6, "coule": 3, "bras": 5, "separe": 1, "desole": 6, "saouler": 1, "pouvais": 2, "rester": 4, "baby": 7, "viennes": 1, "seule": 7, "oublier": 2, "faisons": 2, "quelqu": 5, "ensemble": 15, "pis": 1, "entend": 1, "pleins": 8, "manies": 6, "voyais": 5, "avait": 7, "nada": 5, "rue": 7, "valide": 6, "chauffe": 5, "fout": 7, "contraires": 5, "attirent": 5, "freres": 8, "hommes": 8, "chair": 2, "encule": 1, "rigole": 6, "g": 2, "bg": 1, "folle": 11, "alcool": 6, "commences": 1, "train": 1, "cramer": 1, "embrasse": 1, "vaillants": 1, "biens": 1, "shour": 1, "mama": 59, "desordre": 1, "alonzo": 1, "caillasse": 1, "forces": 1, "ordre": 1, "i": 4, "hab": 10, "rapta": 3, "mic": 3, "foot": 1, "mac": 2, "reviennent": 1, "gratte": 3, "partagent": 1, "or": 4, "coupent": 1, "fous": 13, "terrain": 1, "reves": 2, "terrible": 1, "mesrine": 1, "farines": 1, "guidon": 4, "cache": 2, "pleurer": 2, "dors": 3, "ecoeure": 1, "stick": 2, "galope": 2, "slalome": 2, "salope": 2, "parles": 7, "calote": 2, "rr": 2, "1000": 2, "creve": 2, "deboule": 1, "colle": 2, "boules": 1, "reconnu": 2, "cagoule": 3, "feu": 1, "sent": 4, "poulet": 1, "ciel": 9, "daronne": 1, "foulee": 1, "gays": 1, "refoules": 1, "crise": 1, "fouillent": 1, "enfume": 1, "herbe": 4, "putain": 12, "connu": 8, "moment": 2, "buzz": 4, "essaie": 1, "garder": 1, "brinks": 1, "papet": 1, "fila": 1, "ancienne": 1, "mot": 1, "filade": 1, "laisses": 2, "genre": 2, "mode": 4, "italienne": 1, "gare": 1, "cayenne": 1, "avais": 2, "compris": 2, "casque": 1, "integral": 1, "sois": 5, "stresse": 6, "inquiete": 2, "paquetage": 1, "envoie": 6, "savais": 2, "allais": 3, "sauver": 1, "bitume": 3, "voyous": 1, "ni": 2, "toxicos": 1, "mytho": 1, "corsico": 1, "traine": 9, "bico": 1, "taxer": 1, "france": 2, "nico": 1, "emballer": 1, "bat": 6, "plan": 2, "cul": 5, "rouspetes": 1, "cool": 1, "berner": 1, "ecoutais": 1, "chants": 1, "cerner": 1, "interner": 1, "fermez": 1, "cerne": 1, "presque": 1, "fermes": 2, "dernier": 1, "permission": 1, "grandis": 2, "oublies": 2, "perds": 7, "soces": 1, "gosses": 1, "crosse": 1, "carrure": 1, "lil": 1, "wayne": 1, "chaine": 1, "rick": 1, "ross": 1, "fontfont": 1, "jette": 2, "galets": 1, "bails": 2, "chialer": 1, "sienne": 1, "jarret": 3, "braquo": 1, "z": 2, "jallet": 1, "v": 1, "puce": 1, "palet": 1, "rentres": 1, "tapette": 1, "lacrizeomic": 1, "grave": 3, "chantier": 1, "taffer": 2, "placo": 1, "entendu": 2, "civils": 1, "peau": 2, "branche": 4, "mange": 2, "rateaux": 2, "boite": 4, "sebago": 2, "bord": 3, "mer": 2, "caviar": 2, "pago": 2, "vodka": 6, "detourne": 3, "oblige": 1, "linxer": 1, "man": 3, "vexer": 1, "pourries": 1, "sourire": 4, "aimerais": 4, "passer": 4, "partout": 18, "petite": 1, "souris": 1, "compte": 2, "bonjour": 1, "nouvelles": 3, "amitie": 3, "gachee": 1, "jetee": 1, "poubelle": 1, "prie": 4, "ecarter": 2, "avenir": 2, "flou": 3, "ceux": 8, "partaient": 1, "voler": 2, "carter": 1, "pose": 2, "police": 5, "petee": 1, "repeinte": 1, "polish": 1, "lacrizeomicmek": 1, "gyros": 3, "memes": 1, "broly": 1, "folie": 9, "fier": 9, "bolides": 1, "solide": 3, "sakakini": 1, "lamborghini": 1, "bikini": 1, "ami": 6, "mythomanie": 1, "tony": 4, "manny": 1, "hero": 1, "machin": 3, "cachet": 1, "forts": 2, "cachot": 1, "caches": 1, "murs": 2, "envie": 5, "schlasser": 1, "innove": 1, "james": 1, "bond": 1, "job": 1, "gratter": 2, "blondes": 3, "star": 1, "look": 1, "at": 1, "golf": 1, "sport": 1, "braques": 1, "spar": 1, "faux": 7, "brasses": 1, "num": 3, "quel": 4, "age": 1, "vice": 1, "mel": 2, "trainer": 3, "devenir": 1, "criminel": 1, "kx": 4, "max": 10, "tit": 6, "stunt": 4, "runner": 4, "pute": 4, "secteur": 3, "patrouille": 1, "ninj": 1, "tdm": 1, "clique": 1, "inspecteur": 1, "costaud": 1, "soeur": 2, "meles": 1, "affaires": 1, "braqueur": 1, "traines": 4, "voleurs": 1, "casseurs": 1, "propose": 1, "armer": 1, "savent": 3, "taire": 2, "fument": 2, "autres": 2, "pousse": 1, "accelere": 2, "presse": 1, "meleurs": 1, "decapote": 1, "quartiers": 1, "dedans": 10, "dedicace": 7, "braquent": 6, "dehors": 3, "assurer": 2, "nez": 4, "pattes": 1, "amener": 1, "fumais": 1, "patate": 1, "rif": 1, "pendant": 2, "grattais": 1, "sympathisais": 1, "shmits": 1, "routine": 2, "devenu": 3, "banal": 26, "petou": 1, "banales": 11, "oasis": 2, "fraise": 2, "banane": 1, "ouvre": 1, "vitre": 1, "croise": 2, "fans": 1, "photos": 4, "confiance": 2, "ali": 1, "tempete": 1, "chamelle": 1, "voila": 8, "sac": 1, "chanel": 1, "rose": 2, "tourne": 3, "exploser": 1, "treize": 1, "faim": 8, "poser": 1, "cent": 2, "doigts": 2, "etre": 4, "millionnaire": 1, "nerfs": 3, "siou": 1, "cracher": 1, "moteur": 1, "pana": 1, "coq": 1, "ane": 1, "range": 1, "lame": 1, "craint": 1, "esquiver": 1, "308": 1, "break": 1, "grace": 1, "platine": 2, "ete": 1, "gamos": 2, "meches": 1, "matin": 10, "pense": 39, "endors": 2, "bebe": 4, "faite": 11, "chaque": 4, "cause": 5, "pensait": 2, "dirait": 1, "murit": 1, "malgre": 1, "toto": 28, "ninetta": 26, "magouilles": 1, "copine": 1, "beh": 1, "decois": 1, "caline": 1, "dormais": 1, "vieillir": 1, "plein": 1, "traces": 1, "probemes": 1, "jalouse": 1, "boude": 1, "bout": 1, "bisou": 7, "bouges": 1, "ira": 2, "fera": 1, "voudras": 1, "vente": 2, "jouent": 1, "van": 1, "damme": 1, "souleves": 1, "gendarmes": 1, "bave": 1, "etudes": 1, "bavent": 1, "eduquent": 1, "emboucane": 2, "com": 1, "trou": 1, "prenais": 2, "hulk": 1, "nuques": 1, "parait": 3, "tires": 1, "vises": 1, "devise": 2, "bise": 1, "mettez": 1, "pensees": 1, "ecart": 1, "droit": 1, "voulez": 1, "rassemble": 1, "dessoude": 1, "dessaoule": 1, "tise": 3, "barrettes": 1, "soutifs": 1, "pouki": 1, "couteau": 4, "batte": 6, "rocky": 1, "choquer": 1, "propre": 1, "leches": 1, "chattes": 1, "jonquera": 1, "pomper": 1, "bdh": 1, "pompes": 2, "adore": 1, "garderais": 1, "perso": 1, "cherches": 4, "sales": 1, "celles": 1, "donnent": 1, "derche": 1, "perche": 1, "abiment": 1, "cellule": 1, "nul": 1, "assimile": 1, "fete": 4, "prete": 1, "argent": 2, "claque": 1, "part": 4, "revient": 1, "alcoolise": 2, "smirnoff": 1, "redbull": 1, "to": 1, "ph": 1, "ecoutes": 1, "plains": 1, "jeun": 1, "respecte": 3, "estime": 1, "ecrire": 2, "texte": 1, "affut": 1, "puenta": 2, "fenetre": 1, "maison": 2, "arret": 3, "dedicacerai": 1, "saint": 1, "jean": 1, "ghetto": 8, "phenomene": 3, "ouest": 16, "kush": 3, "gout": 1, "falaise": 1, "fraiche": 2, "tellement": 2, "dingue": 1, "vitesses": 1, "deesse": 1, "maitresse": 1, "detresse": 1, "amnesia": 5, "malaise": 5, "balaise": 8, "white": 1, "widow": 1, "tire": 2, "rideau": 1, "comprendre": 2, "rivaux": 1, "critical": 1, "critiques": 1, "tropical": 1, "medical": 1, "musical": 1, "couleur": 1, "carte": 1, "vitale": 1, "bruits": 1, "courent": 1, "tetes": 3, "perde": 1, "nord": 1, "bijou": 17, "serre": 3, "rendre": 2, "lache": 2, "serres": 1, "presente": 1, "hauts": 4, "laisser": 1, "choix": 2, "content": 1, "voix": 2, "habillee": 1, "pyjama": 1, "coiffee": 1, "pinces": 1, "etincelle": 1, "cuisine": 2, "resine": 2, "hallucine": 3, "dessinent": 2, "piscine": 2, "lady": 3, "ressentait": 1, "douleurs": 2, "avis": 1, "appris": 2, "couleurs": 2, "mi": 4, "amor": 1, "agi": 1, "faisais": 1, "magie": 7, "pire": 6, "avoue": 6, "dehanche": 1, "k": 1, "o": 1, "timide": 3, "plait": 5, "bah": 2, "parlons": 1, "occupe": 2, "ballon": 1, "ferais": 1, "devient": 3, "jack": 4, "coca": 3, "llez": 6, "amene": 3, "restau": 3, "occas": 3, "bonnes": 1, "jure": 1, "ailes": 4, "sourd": 1, "loge": 1, "rempli": 4, "frigo": 1, "commissariat": 1, "idiot": 1, "drole": 2, "life": 15, "maman": 5, "attend": 2, "essayer": 1, "gater": 2, "rater": 1, "inciter": 1, "papa": 2, "pareil": 4, "larme": 1, "parents": 2, "profites": 1, "eloigne": 8, "gache": 1, "ravi": 1, "pars": 1, "ravins": 1, "ventre": 1, "pres": 1, "entendre": 1, "raler": 1, "attendu": 2, "libere": 1, "pere": 3, "arretes": 1, "parce": 4, "civ": 1, "guettent": 1, "instant": 3, "attendant": 1, "signe": 5, "criait": 1, "absence": 1, "dar": 1, "lies": 1, "jo": 6, "angelina": 6, "mental": 6, "sandra": 6, "paoli": 6, "resonne": 1, "ressemble": 1, "caractere": 1, "sentiments": 2, "semble": 1, "ter": 2, "plaint": 1, "franchement": 4, "insomnie": 9, "souvent": 2, "ennuie": 3, "deplu": 1, "degats": 1, "souffrir": 2, "ouvrir": 1, "bisous": 1, "gates": 1, "craquer": 1, "made": 1, "selle": 1, "longtemps": 1, "kalenji": 1, "lundi": 1, "tester": 3, "bolide": 1, "brolique": 1, "affole": 1, "fole": 2, "zen": 3, "picole": 2, "cole": 2, "voiles": 2, "large": 1, "nage": 3, "serai": 3, "maille": 3, "ailles": 1, "etats": 1, "laissera": 1, "ferai": 7, "eh": 37, "yo": 35, "voudra": 1, "douterai": 1, "premiers": 1, "pourrais": 6, "offrirais": 1, "chiens": 1, "thune": 1, "donnerais": 1, "marre": 2, "enraye": 1, "adapte": 48, "refont": 10, "loups": 10, "temperature": 1, "bouillante": 1, "khouya": 1, "situation": 1, "revenu": 1, "brulant": 1, "troublant": 1, "beat": 4, "tass": 1, "arrache": 2, "bai": 2, "pe": 3, "pese": 1, "be": 2, "best": 2, "queue": 1, "rond": 1, "disque": 2, "gova": 1, "sera": 2, "salvatore": 1, "deter": 1, "teum": 2, "casser": 1, "annee": 7, "derniere": 1, "aide": 9, "galere": 15, "salaire": 1, "traque": 1, "net": 1, "flic": 1, "poursuite": 3, "devoile": 1, "pablo": 1, "infos": 2, "raconte": 7, "lacheraient": 1, "malheur": 6, "cesse": 2, "raleur": 1, "soit": 6, "bosses": 1, "branleur": 1, "manieres": 1, "ailleurs": 4, "manient": 1, "fer": 1, "ferrailleur": 1, "nier": 3, "allies": 2, "industry": 1, "carcasse": 1, "brise": 2, "dessus": 1, "gangs": 1, "brule": 1, "azote": 1, "ramenes": 1, "perdues": 1, "passes": 2, "annees": 2, "blocs": 2, "halls": 1, "condamnes": 1, "paye": 2, "villa": 1, "tite": 1, "fille": 2, "chacals": 1, "gares": 1, "egare": 2, "f": 1, "r": 1, "diff": 1, "surface": 1, "severe": 1, "tacle": 2, "bons": 2, "souvenirs": 1, "date": 1, "move": 3, "oseille": 3, "rode": 1, "night": 10, "khabat": 8, "mortadon": 1, "dure": 2, "planer": 4, "marley": 4, "rondes": 3, "enfonce": 3, "manques": 3, "ange": 2, "faute": 2, "murders": 1, "perdre": 1, "effort": 1, "malmenes": 1, "facile": 3, "lire": 1, "peines": 1, "decu": 3, "salades": 3, "corazon": 3, "balade": 5, "deja": 4, "cauchemar": 2, "ris": 2, "pleure": 4, "vivre": 3, "seconde": 2, "raisons": 1, "mienne": 1, "ignore": 7, "rengaine": 1, "degaines": 1, "saigne": 1, "virer": 1, "morgue": 1, "excusez": 1, "revendu": 1, "minots": 2, "balader": 1, "glock": 1, "idee": 1, "charbonner": 2, "bloc": 3, "respect": 1, "youma": 1, "protege": 2, "cocaine": 1, "veines": 2, "bourriche": 1, "doc": 1, "gaga": 1, "depanne": 1, "tiop": 1, "soso": 2, "maness": 1, "kamikaze": 2, "autoroute": 1, "phare": 1, "xenon": 1, "condes": 1, "prenom": 1, "charbon": 1, "deregle": 6, "rabattre": 6, "voitures": 6, "bac": 6, "abattent": 6, "ratatata": 6, "gante": 1, "depend": 1, "frequenter": 1, "etoiles": 2, "barre": 1, "descends": 2, "pourra": 1, "pardonner": 1, "cramponne": 1, "boites": 1, "boire": 3, "tamponner": 1, "sniffer": 1, "attrapes": 1, "crampes": 2, "foireux": 1, "ovni": 33, "parti": 1, "squatte": 1, "beton": 1, "bes": 1, "tom": 2, "sers": 2, "retourne": 2, "veston": 1, "reconnaissent": 1, "honneurs": 1, "vivons": 1, "entre": 1, "flutes": 1, "mitonne": 1, "etonne": 1, "promo": 1, "rime": 1, "arriver": 1, "serait": 1, "cassent": 4, "jalousent": 1, "truc": 1, "comprends": 2, "cru": 1, "attente": 1, "albums": 1, "sombre": 5, "aurons": 1, "visons": 1, "critiquent": 1, "batard": 1, "chenef": 2, "attarde": 1, "grilles": 1, "radar": 1, "connue": 1, "plaie": 1, "aimeraient": 1, "remue": 1, "deuhman": 1, "tits": 9, "gantes": 9, "parcours": 7, "brigante": 7, "delire": 2, "vanter": 1, "delits": 2, "inventer": 1, "scanne": 1, "grandi": 1, "cotoie": 1, "sort": 6, "six": 1, "taf": 1, "black": 1, "but": 2, "chiffre": 1, "gifle": 1, "foule": 1, "agite": 1, "fire": 2, "plaisir": 2, "soutient": 1, "flyer": 1, "attire": 5, "mentir": 1, "pouvoir": 1, "terter": 3, "quittent": 1, "zik": 1, "classique": 1, "peine": 3, "debut": 3, "poucave": 1, "week": 1, "end": 1, "seum": 1, "ferme": 2, "vaut": 2, "apercois": 1, "culs": 2, "hachek": 1, "aucune": 1, "recule": 1, "entoure": 1, "arrives": 1, "goute": 1, "thunes": 1, "prochain": 6, "aidera": 6, "aimera": 6, "separes": 1, "proche": 1, "offrir": 1, "terre": 1, "pourrir": 1, "sentiment": 1, "trahison": 1, "jalousie": 6, "aimais": 1, "probleme": 1, "vingtaine": 1, "enfant": 1, "fascine": 1, "sable": 1, "vagues": 1, "efface": 1, "nie": 1, "jnounes": 1, "cagoules": 1, "poulets": 1, "bouee": 1, "souhait": 1, "soulier": 1, "palier": 1, "fallait": 4, "balaye": 1, "aaliyah": 1, "avoues": 1, "clip": 1, "scie": 1, "bitches": 1, "cirer": 2, "ennemi": 1, "dechire": 1, "iceberg": 1, "chavire": 1, "irai": 2, "bats": 3, "ex": 1, "gire": 1, "givres": 1, "fuite": 1, "merce": 44, "lecher": 1, "traverser": 1, "levez": 1, "trahir": 1, "schiro": 1, "joint": 1, "quille": 1, "sirop": 1, "mettre": 5, "lu": 2, "pirlo": 1, "habille": 1, "clips": 1, "maquille": 1, "haine": 2, "micro": 1, "machine": 1, "achete": 1, "brulais": 1, "feux": 1, "gta": 5, "degoutes": 1, "panamera": 1, "rappeur": 1, "miracles": 1, "acteurs": 1, "reviens": 1, "chanter": 1, "reviendra": 1, "sangoku": 1, "nourri": 1, "manges": 1, "celle": 3, "pourri": 1, "assure": 1, "risques": 1, "om": 1, "poeme": 1, "buter": 1, "sosa": 1, "chantent": 1, "comiques": 1, "mouille": 1, "dossard": 1, "sommeil": 7, "ghe": 6, "tto": 1, "soleil": 3, "biff": 1, "direct": 3, "bedo": 1, "metaux": 1, "untel": 2, "agis": 1, "affaire": 1, "ecopes": 1, "flow": 2, "floppes": 2, "partage": 2, "croque": 2, "bizarres": 2, "concert": 1, "guichets": 1, "ibiza": 1, "pete": 3, "po": 1, "gardez": 1, "peche": 1, "mandat": 2, "depot": 1, "gp": 1, "verra": 1, "bientot": 1, "donnes": 6, "crocs": 7, "voyou": 3, "jnoun": 1, "genou": 1, "emballe": 1, "recale": 1, "vafencul": 1, "retrouve": 2, "tele": 1, "atterrir": 1, "deale": 1, "combien": 1, "kils": 1, "mois": 1, "reservee": 1, "preserver": 1, "servait": 1, "srv": 1, "trouver": 1, "donnerai": 1, "tueraient": 1, "puree": 1, "reconnait": 1, "duree": 1, "jures": 1, "jurer": 1, "effrite": 1, "produit": 1, "porte": 1, "fermee": 1, "passee": 1, "conduit": 1, "mythomanes": 1, "boy": 1, "controle": 1, "manettes": 1, "taffe": 1, "chinois": 1, "h24": 1, "carres": 1, "remballez": 1, "bip": 2, "feles": 1, "friz": 1, "promene": 1, "demandes": 1, "assumes": 1, "dalle": 1, "reveille": 1, "doucement": 1, "accord": 1, "arretez": 1, "perdez": 1, "votre": 1, "morts": 1, "tentant": 1, "ruelles": 1, "resonnent": 1, "pan": 2, "braquer": 1, "4": 5, "reprendre": 1, "determines": 1, "dom": 1, "shab": 1, "bonhommes": 1, "direction": 1, "jonq": 1, "decolle": 1, "montes": 1, "gouter": 1, "kicke": 1, "rai": 1, "dancehall": 1, "rire": 1, "wiggle": 2, "sexe": 2, "bigle": 1, "destresse": 1, "vexes": 1, "sinon": 1, "next": 1, "noyer": 1, "ame": 1, "bitch": 1, "picore": 1, "accompagne": 1, "accroche": 1, "call": 1, "of": 1, "refait": 1, "billet": 1, "mauve": 1, "sale": 1, "economie": 1, "occupent": 1, "bella": 1, "aram": 1, "quatre": 5, "heures": 1, "barrer": 1, "tare": 1, "tarot": 1, "paie": 1, "avocat": 1, "paros": 1, "braves": 1, "pou": 2, "pigeons": 1, "toutous": 1, "parlu": 1, "foufoune": 1, "veine": 1, "chouchou": 1, "decoupent": 1, "poutous": 1, "cambou": 1, "laches": 1, "bambou": 1, "ecouter": 1, "niques": 1, "choupes": 1, "detourner": 1, "gow": 1, "nympho": 1, "pecs": 1, "danses": 1, "mambo": 1, "speed": 1, "abuse": 1, "cc": 1, "fessees": 1, "showcase": 2, "coude": 1, "frappe": 1, "bosse": 1, "dansent": 1, "moose": 1, "usb": 1, "bluetooth": 1, "envoute": 1, "coucou": 1, "disquette": 1, "ecris": 6, "represente": 6, "tess": 7, "aise": 6, "rabaisses": 3, "faisant": 3, "flouze": 1, "sorcellerie": 1, "couscous": 1, "sortent": 1, "guns": 1, "tailler": 1, "ven": 1, "aqui": 1, "maquis": 1, "kheys": 1, "pleut": 1, "bouteilles": 3, "foutu": 1, "couler": 1, "cagouler": 1, "trouer": 1, "reponds": 2, "ecroues": 1, "vitesse": 1, "cubes": 1, "brunes": 1, "realise": 1, "maisons": 1, "disques": 1, "kiffent": 1, "enerver": 1, "longue": 1, "telephone": 1, "tb": 1, "paquette": 1, "aurait": 1, "pu": 1, "clark": 1, "kent": 1, "medias": 1, "harcelent": 1, "charbons": 1, "sarcelles": 1, "flash": 1, "tailleur": 1, "valeur": 14, "appellerais": 1, "caisse": 1, "millions": 1, "certains": 1, "detestent": 1, "mignon": 1, "drames": 1, "mauvaise": 1, "interieur": 1, "charme": 4, "finie": 1, "mots": 6, "rendu": 6, "lalalalalalala": 8, "pourtant": 2, "comprennent": 1, "promis": 1, "desespere": 1, "mechant": 1, "croyais": 2, "fendu": 1, "esprit": 1, "tordu": 1, "aurais": 1, "kodo": 14, "espace": 2, "classe": 2, "allo": 2, "pepito": 4, "punto": 2, "putos": 2, "azonto": 2, "pulco": 2, "coke": 2, "cherie": 2, "coco": 2, "croquer": 2, "coquet": 2, "aprem": 4, "poule": 4, "claques": 4, "partages": 2, "soutiens": 2, "portes": 2, "shirt": 2, "location": 3, "consommation": 2, "gratuite": 2, "benjamin": 2, "mende": 2, "ennuis": 2, "merci": 2, "bambino": 2, "rouler": 2, "pied": 3, "reprends": 2, "biberon": 2, "playa": 4, "lit": 4, "plane": 4, "permis": 6, "2015": 1, "soucis": 4, "envoies": 1, "angoisse": 1, "crazy": 1, "quitter": 1, "cauchemars": 1, "eviter": 1, "rayon": 1, "obliger": 1, "taleur": 1, "remarquer": 1, "aiderais": 1, "chanson": 1, "jeter": 1, "sorts": 1, "notre": 1, "jalouser": 1, "copines": 1, "permettre": 2, "leurs": 1, "timiniks": 2, "physique": 2, "voient": 1, "brave": 1, "milite": 2, "neuf": 1, "milli": 2, "guillis": 2, "feeling": 2, "causes": 1, "bruit": 1, "gauche": 1, "tas": 1, "caramel": 1, "again": 1, "ml": 3, "frank": 1, "elvi": 1, "oubliez": 12, "saute": 4, "baiser": 4, "commence": 4, "peser": 12, "rafale": 1, "ensorcele": 1, "costauds": 1, "salle": 1, "mises": 1, "scene": 1, "descendre": 1, "harcele": 1, "fane": 1, "hantise": 1, "flouzes": 1, "parc": 4, "guetteur": 1, "chaise": 1, "tises": 1, "viennent": 1, "musique": 2, "signer": 1, "usine": 2, "freestyles": 1, "uzi": 2, "frangin": 1, "lucine": 1, "douche": 1, "naturelle": 1, "rouge": 1, "levres": 1, "fievre": 1, "ait": 1, "jeune": 1, "vierge": 1, "entretient": 1, "cavaler": 1, "prefere": 3, "copain": 1, "kitte": 1, "boit": 1, "goudes": 1, "hood": 1, "parloirs": 1, "bords": 4, "larmes": 4, "sentie": 4, "abandonnee": 4, "beaute": 3, "donner": 3, "venue": 1, "franco": 1, "tient": 1, "poussette": 1, "dettes": 1, "daron": 1, "garant": 1, "miami": 1, "preavis": 1, "retournee": 1, "occasion": 1, "fiat": 1, "500": 1, "bastons": 1, "bracelet": 1, "garcon": 1, "alice": 1, "pays": 1, "merveilles": 1, "enerve": 1, "boco": 1, "merite": 1, "maf": 1, "askip": 1, "guidonne": 2, "sheitan": 2, "mythonne": 2, "camp": 2, "irais": 2, "attirait": 2, "vecue": 2, "mentirais": 1, "fusee": 1, "dira": 1, "mirage": 1, "travers": 1, "virage": 1, "rage": 1, "tof": 1, "rabaissent": 1, "baleze": 1, "agresse": 1, "grossiste": 1, "aussi": 2, "enfument": 1, "chicha": 1, "ours": 1, "mo": 1, "heros": 1, "quitterai": 1, "pilote": 1, "meuf": 1, "passager": 1, "culotte": 1, "deteste": 1, "testent": 1, "tasses": 1, "flechent": 1, "jalouses": 1, "frappes": 1, "casses": 1}}